LICENSE.txt
MANIFEST.in
README.md
requirements.txt
setup.cfg
setup.py
bubuku/__init__.py
bubuku/broker.py
bubuku/cli.py
bubuku/communicate.py
bubuku/config.py
bubuku/controller.py
bubuku/controller_api.py
bubuku/daemon.py
bubuku/env_provider.py
bubuku/id_generator.py
bubuku/process.py
bubuku/utils.py
bubuku.egg-info/PKG-INFO
bubuku.egg-info/SOURCES.txt
bubuku.egg-info/dependency_links.txt
bubuku.egg-info/entry_points.txt
bubuku.egg-info/requires.txt
bubuku.egg-info/top_level.txt
bubuku/aws/__init__.py
bubuku/aws/cluster_config.py
bubuku/aws/ec2_node_launcher.py
bubuku/aws/ip_address_allocator.py
bubuku/aws/node.py
bubuku/features/__init__.py
bubuku/features/data_size_stats.py
bubuku/features/metric_collector.py
bubuku/features/migrate.py
bubuku/features/remote_exec.py
bubuku/features/restart_if_dead.py
bubuku/features/restart_on_zk_change.py
bubuku/features/rolling_restart.py
bubuku/features/swap_partitions.py
bubuku/features/terminate.py
bubuku/features/rebalance/__init__.py
bubuku/features/rebalance/broker.py
bubuku/features/rebalance/change.py
bubuku/features/rebalance/change_simple.py
bubuku/features/rebalance/check.py
bubuku/zookeeper/__init__.py
bubuku/zookeeper/exhibitor.py
instance_control/__init__.py
instance_control/bubuku_cluster.py
instance_control/config.py
instance_control/node.py
instance_control/piu.py
instance_control/volume.py
instance_control/aws/__init__.py
instance_control/aws/ec2_node.py
instance_control/aws/iam.py
instance_control/aws/metric.py
instance_control/aws/security_group.py
instance_control/aws/subnet.py
instance_control/aws/taupage.py
instance_control/command/__init__.py
instance_control/command/attach.py
instance_control/command/create.py
instance_control/command/get.py
instance_control/command/terminate.py
instance_control/command/upgrade.py