Metadata-Version: 1.1
Name: bubuku
Version: 0.10.35
Summary: AWS support for kafka broker
Home-page: https://github.com/zalando-incubator/bubuku
Author: Dmitry Sorokin
Author-email: dmitriy.sorokin@zalando.de
License: Apache License 2.0
Keywords: aws kafka supervisor
Platform: UNKNOWN
Classifier: Development Status :: 3 - Alpha
Classifier: Environment :: Console
Classifier: Intended Audience :: Developers
Classifier: Intended Audience :: System Administrators
Classifier: License :: OSI Approved :: Apache Software License
Classifier: Operating System :: POSIX :: Linux
Classifier: Programming Language :: Python
Classifier: Programming Language :: Python :: 3.4
Classifier: Programming Language :: Python :: Implementation :: CPython
